getnet/__init__.py
getnet/utils.py
getnet/application/__init__.py
getnet/application/dtos/__init__.py
getnet/application/dtos/authentication.py
getnet/application/dtos/card_bin.py
getnet/application/dtos/card_token.py
getnet/application/dtos/card_verification.py
getnet/application/dtos/customer.py
getnet/application/dtos/pix.py
getnet/domain/__init__.py
getnet/domain/authentication/__init__.py
getnet/domain/authentication/authentication.py
getnet/domain/card_bin/__init__.py
getnet/domain/card_bin/card_bin.py
getnet/domain/cards/__init__.py
getnet/domain/cards/card.py
getnet/domain/cards/card_response.py
getnet/domain/cards/service.py
getnet/domain/cards/status.py
getnet/domain/customers/__init__.py
getnet/domain/customers/address.py
getnet/domain/customers/customer.py
getnet/domain/customers/customer_response.py
getnet/domain/customers/service.py
getnet/domain/device/__init__.py
getnet/domain/device/device.py
getnet/domain/payments/__init__.py
getnet/domain/payments/customer.py
getnet/domain/payments/order.py
getnet/domain/payments/payment_response.py
getnet/domain/payments/credit/__init__.py
getnet/domain/payments/credit/card.py
getnet/domain/payments/credit/credit.py
getnet/domain/payments/credit/credit_adjust.py
getnet/domain/payments/credit/credit_cancel.py
getnet/domain/payments/credit/credit_capture.py
getnet/domain/payments/credit/credit_response.py
getnet/domain/payments/credit/service.py
getnet/domain/payments/pix/__init__.py
getnet/domain/payments/pix/pix.py
getnet/domain/payments/pix/pix_response.py
getnet/domain/payments/pix/service.py
getnet/domain/services/__init__.py
getnet/domain/services/service.py
getnet/domain/token/__init__.py
getnet/domain/token/card_number.py
getnet/domain/token/card_token.py
getnet/domain/token/service.py
getnet/domain/usecases/__init__.py
getnet/domain/usecases/client/__init__.py
getnet/domain/usecases/client/get_client.py
getnet/domain/usecases/environment/__init__.py
getnet/domain/usecases/environment/get_environment.py
getnet_python-3.5.dist-info/LICENSE
getnet_python-3.5.dist-info/METADATA
getnet_python-3.5.dist-info/WHEEL
getnet_python-3.5.dist-info/top_level.txt
getnet_python-3.5.dist-info/RECORD
