Metadata-Version: 2.1
Name: getnet-python
Version: 3.5
Summary: A Getnet SDK
Home-page: https://github.com/FVitor7/getnet-python
Author: Fabio Vitor
Author-email: fabvitor2010@gmail.com
License: UNKNOWN
Platform: UNKNOWN
Classifier: Intended Audience :: Developers
Classifier: Natural Language :: English
Classifier: License :: OSI Approved :: MIT License
Classifier: Programming Language :: Python
Classifier: Programming Language :: Python :: 3
Requires-Python: >=3.6
License-File: LICENSE
Requires-Dist: requests (>=2.0.0)
Requires-Dist: requests-oauthlib (>=1.2.0)
Requires-Dist: python-dateutil (==2.8.1)
